kbase/auth.py
kbase/_auth/exceptions.py
kbase/_auth/models.py
kbase/_auth/_async/client.py
kbase/_auth/_sync/client.py
kbase_auth_client-0.1.1.dist-info/METADATA
kbase_auth_client-0.1.1.dist-info/WHEEL
kbase_auth_client-0.1.1.dist-info/licenses/LICENSE.md
kbase_auth_client-0.1.1.dist-info/RECORD
