Metadata-Version: 2.4
Name: kbase-auth-client
Version: 0.1.1
Summary: Client for the KBase Authentication Service
Project-URL: Homepage, https://github.com/kbase/auth2_client_python
Project-URL: Repository, https://github.com/kbase/auth2_client_python
Project-URL: Issues, https://github.com/kbase/auth2_client_python/issues
Author: KBase Development Team
License: MIT
License-File: LICENSE.md
Classifier: License :: OSI Approved :: MIT License
Classifier: Operating System :: OS Independent
Classifier: Programming Language :: Python :: 3
Requires-Python: >=3.12
Requires-Dist: cacheout>=0.16.0
Requires-Dist: httpx>=0.28.1
